{"errors":[],"warnings":[],"namedChunkGroups":{"app":{"chunks":[9,0,8,2],"assets":["webpack-runtime-415f4477bb21ec3119ea.js","webpack-runtime-415f4477bb21ec3119ea.js.map","styles.bacf31bb6a53d8449d4a.css","styles-9b6f388623a2ec93d35f.js","styles-9b6f388623a2ec93d35f.js.map","framework-75da9754c2a76bbaf08a.js","framework-75da9754c2a76bbaf08a.js.map","app-534eb45e742d449757cf.js","app-534eb45e742d449757cf.js.map"],"children":{},"childAssets":{}},"component---src-pages-404-js":{"chunks":[0,1,3],"assets":["styles.bacf31bb6a53d8449d4a.css","styles-9b6f388623a2ec93d35f.js","styles-9b6f388623a2ec93d35f.js.map","commons-bbe44f3a7a936e48a1b8.js","commons-bbe44f3a7a936e48a1b8.js.map","component---src-pages-404-js-0a139d61345f1ac44288.js","component---src-pages-404-js-0a139d61345f1ac44288.js.map"],"children":{},"childAssets":{}},"component---src-pages-about-js":{"chunks":[0,1,4],"assets":["styles.bacf31bb6a53d8449d4a.css","styles-9b6f388623a2ec93d35f.js","styles-9b6f388623a2ec93d35f.js.map","commons-bbe44f3a7a936e48a1b8.js","commons-bbe44f3a7a936e48a1b8.js.map","component---src-pages-about-js-768fcac0dde100172641.js","component---src-pages-about-js-768fcac0dde100172641.js.map"],"children":{},"childAssets":{}},"component---src-pages-contact-js":{"chunks":[0,1,5],"assets":["styles.bacf31bb6a53d8449d4a.css","styles-9b6f388623a2ec93d35f.js","styles-9b6f388623a2ec93d35f.js.map","commons-bbe44f3a7a936e48a1b8.js","commons-bbe44f3a7a936e48a1b8.js.map","component---src-pages-contact-js-66db06ac98dbc3ef60c1.js","component---src-pages-contact-js-66db06ac98dbc3ef60c1.js.map"],"children":{},"childAssets":{}},"component---src-pages-index-js":{"chunks":[0,1,6],"assets":["styles.bacf31bb6a53d8449d4a.css","styles-9b6f388623a2ec93d35f.js","styles-9b6f388623a2ec93d35f.js.map","commons-bbe44f3a7a936e48a1b8.js","commons-bbe44f3a7a936e48a1b8.js.map","component---src-pages-index-js-8dd972bec81ec8b48175.js","component---src-pages-index-js-8dd972bec81ec8b48175.js.map"],"children":{},"childAssets":{}},"component---src-pages-portfolio-js":{"chunks":[0,1,7],"assets":["styles.bacf31bb6a53d8449d4a.css","styles-9b6f388623a2ec93d35f.js","styles-9b6f388623a2ec93d35f.js.map","commons-bbe44f3a7a936e48a1b8.js","commons-bbe44f3a7a936e48a1b8.js.map","component---src-pages-portfolio-js-f21f531a92ae4c0a0d3d.js","component---src-pages-portfolio-js-f21f531a92ae4c0a0d3d.js.map"],"children":{},"childAssets":{}}},"assetsByChunkName":{"app":["webpack-runtime-415f4477bb21ec3119ea.js","styles.bacf31bb6a53d8449d4a.css","styles-9b6f388623a2ec93d35f.js","framework-75da9754c2a76bbaf08a.js","app-534eb45e742d449757cf.js"],"component---src-pages-404-js":["styles.bacf31bb6a53d8449d4a.css","styles-9b6f388623a2ec93d35f.js","commons-bbe44f3a7a936e48a1b8.js","component---src-pages-404-js-0a139d61345f1ac44288.js"],"component---src-pages-about-js":["styles.bacf31bb6a53d8449d4a.css","styles-9b6f388623a2ec93d35f.js","commons-bbe44f3a7a936e48a1b8.js","component---src-pages-about-js-768fcac0dde100172641.js"],"component---src-pages-contact-js":["styles.bacf31bb6a53d8449d4a.css","styles-9b6f388623a2ec93d35f.js","commons-bbe44f3a7a936e48a1b8.js","component---src-pages-contact-js-66db06ac98dbc3ef60c1.js"],"component---src-pages-index-js":["styles.bacf31bb6a53d8449d4a.css","styles-9b6f388623a2ec93d35f.js","commons-bbe44f3a7a936e48a1b8.js","component---src-pages-index-js-8dd972bec81ec8b48175.js"],"component---src-pages-portfolio-js":["styles.bacf31bb6a53d8449d4a.css","styles-9b6f388623a2ec93d35f.js","commons-bbe44f3a7a936e48a1b8.js","component---src-pages-portfolio-js-f21f531a92ae4c0a0d3d.js"]}}